[{"id":1,"name":"Arnuad","gender":"Male"},
{"id":2,"name":"Celesta","gender":"Female"},
{"id":3,"name":"Yetty","gender":"Bigender"},
{"id":4,"name":"Dollie","gender":"Agender"},
{"id":5,"name":"Englebert","gender":"Male"},
{"id":6,"name":"Shari","gender":"Female"},
{"id":7,"name":"Shelby","gender":"Male"},
{"id":8,"name":"Deanna","gender":"Female"},
{"id":9,"name":"Celine","gender":"Female"},
{"id":10,"name":"Tammara","gender":"Female"},
{"id":11,"name":"Corny","gender":"Male"},
{"id":12,"name":"Constantin","gender":"Male"},
{"id":13,"name":"Keslie","gender":"Female"},
{"id":14,"name":"Godfry","gender":"Male"},
{"id":15,"name":"Patrice","gender":"Female"},
{"id":16,"name":"Siouxie","gender":"Female"},
{"id":17,"name":"Deana","gender":"Female"},
{"id":18,"name":"Cathee","gender":"Female"},
{"id":19,"name":"Cesya","gender":"Female"},
{"id":20,"name":"Alleen","gender":"Female"},
{"id":21,"name":"Lindsey","gender":"Male"},
{"id":22,"name":"Claire","gender":"Female"},
{"id":23,"name":"Kaja","gender":"Bigender"},
{"id":24,"name":"Hilary","gender":"Male"},
{"id":25,"name":"Fredericka","gender":"Female"},
{"id":26,"name":"Park","gender":"Male"},
{"id":27,"name":"Mindy","gender":"Female"},
{"id":28,"name":"Eldredge","gender":"Genderfluid"},
{"id":29,"name":"Friederike","gender":"Female"},
{"id":30,"name":"Alexandro","gender":"Male"},
{"id":31,"name":"Merlina","gender":"Female"},
{"id":32,"name":"Quincy","gender":"Male"},
{"id":33,"name":"Del","gender":"Genderqueer"},
{"id":34,"name":"Orelie","gender":"Female"},
{"id":35,"name":"Donica","gender":"Female"},
{"id":36,"name":"Myrvyn","gender":"Male"},
{"id":37,"name":"Rob","gender":"Male"},
{"id":38,"name":"Alister","gender":"Male"},
{"id":39,"name":"Horatia","gender":"Female"},
{"id":40,"name":"Catlee","gender":"Female"},
{"id":41,"name":"Alena","gender":"Female"},
{"id":42,"name":"Teddie","gender":"Female"},
{"id":43,"name":"Abel","gender":"Male"},
{"id":44,"name":"Vinnie","gender":"Genderqueer"},
{"id":45,"name":"Emmet","gender":"Male"},
{"id":46,"name":"Gianina","gender":"Agender"},
{"id":47,"name":"April","gender":"Non-binary"},
{"id":48,"name":"Hali","gender":"Female"},
{"id":49,"name":"Mano","gender":"Male"},
{"id":50,"name":"Antone","gender":"Polygender"}]